{
  "form_id": "user_registration_form",
  "form_title": "用户注册表单",
  "timestamp": "2026-01-30 22:30:54",
  "data": {
    "name": {
      "label": "姓名",
      "type": "text",
      "value": "aa"
    },
    "email": {
      "label": "邮箱地址",
      "type": "text",
      "value": "aa"
    },
    "country": {
      "label": "选择国家/地区",
      "type": "single_choice",
      "value": "us"
    },
    "interests": {
      "label": "选择您的兴趣",
      "type": "multi_choice",
      "value": []
    },
    "subscription": {
      "label": "选择订阅类型",
      "type": "single_choice",
      "value": "free"
    },
    "bio": {
      "label": "个人简介",
      "type": "text",
      "value": "aa"
    }
  }
}